supervisord_dependent_startup/__init__.py
supervisord_dependent_startup/__main__.py
supervisord_dependent_startup/__version.py
supervisord_dependent_startup/supervisord_dependent_startup.py
supervisord_dependent_startup/tests/__init__.py
supervisord_dependent_startup/tests/common.py
supervisord_dependent_startup/tests/config_utils.py
supervisord_dependent_startup/tests/helpers.py
supervisord_dependent_startup/tests/log_color_fmt.py
supervisord_dependent_startup/tests/log_utils.py
supervisord_dependent_startup/tests/test_dependent_startup.py
supervisord_dependent_startup/tests/test_dependent_startup_events.py
supervisord_dependent_startup/tests/test_service_handler.py
supervisord_dependent_startup/tests/utils.py
supervisord_dependent_startup-1.4.0.dist-info/LICENSE
supervisord_dependent_startup-1.4.0.dist-info/METADATA
supervisord_dependent_startup-1.4.0.dist-info/WHEEL
supervisord_dependent_startup-1.4.0.dist-info/entry_points.txt
supervisord_dependent_startup-1.4.0.dist-info/top_level.txt
supervisord_dependent_startup-1.4.0.dist-info/RECORD
