Metadata-Version: 2.1
Name: supervisord-dependent-startup
Version: 1.4.0
Summary: A plugin for Supervisor that allows starting up services after dependent services have reached specific states. Based on ordered-startup-supervisord by Jason Corbett
Home-page: https://github.com/bendikro/supervisord-dependent-startup
Author: Bendik Rønning Opstad
Author-email: bro.devel@gmail.com
License: Apache Software License v2
Platform: UNKNOWN
Classifier: License :: OSI Approved :: Apache Software License
Classifier: Programming Language :: Python :: 2.7
Classifier: Programming Language :: Python :: 3.4
Classifier: Programming Language :: Python :: 3.5
Classifier: Programming Language :: Python :: 3.6
Classifier: Programming Language :: Python :: 3.7
Classifier: Topic :: System :: Boot :: Init
Classifier: Environment :: Plugins
Requires-Dist: supervisor (>=3.2.0)
Requires-Dist: toposort (>=1.5)
